pythopesis/__init__.py
pythopesis/add.py
pythopesis-0.0.0a1.dev3.dist-info/METADATA
pythopesis-0.0.0a1.dev3.dist-info/WHEEL
pythopesis-0.0.0a1.dev3.dist-info/licenses/LICENSE
pythopesis-0.0.0a1.dev3.dist-info/RECORD
