Metadata-Version: 2.4
Name: pythopesis
Version: 0.0.0a1.dev3
Summary: A Python CLI & Python Package for managing research project templates and configurations.
Project-URL: Homepage, https://github.com/harry-campion/pythopesis
Project-URL: Repository, https://github.com/harry-campion/pythopesis
Project-URL: Issues, https://github.com/harry-campion/pythopesis/issues
Author: Harry Campion
License: MIT
License-File: LICENSE
Keywords: project
Classifier: Development Status :: 3 - Alpha
Classifier: Intended Audience :: Developers
Classifier: License :: OSI Approved :: MIT License
Classifier: Operating System :: OS Independent
Classifier: Programming Language :: Python :: 3
Classifier: Programming Language :: Python :: 3 :: Only
Classifier: Programming Language :: Python :: 3.11
Classifier: Programming Language :: Python :: 3.12
Classifier: Programming Language :: Python :: 3.13
Classifier: Programming Language :: Python :: 3.14
Classifier: Topic :: Software Development :: Build Tools
Requires-Python: >=3.11
Provides-Extra: dev
Requires-Dist: marimo==0.18.1; extra == 'dev'
Requires-Dist: pdoc>=16.0.0; extra == 'dev'
Requires-Dist: pre-commit==4.5.0; extra == 'dev'
Requires-Dist: pytest-cov>=7.0.0; extra == 'dev'
Requires-Dist: pytest-html>=4.1.1; extra == 'dev'
Requires-Dist: pytest==9.0.1; extra == 'dev'
